bme280pi/__init__.py
bme280pi/physics.py
bme280pi/raspberry_pi_version.py
bme280pi/readout.py
bme280pi/sensor.py
test/__init__.py
test/physics.py
test/raspberry_pi_version.py
test/readout.py
test/sensor.py
bme280pi-1.1.2.dist-info/LICENSE
bme280pi-1.1.2.dist-info/METADATA
bme280pi-1.1.2.dist-info/WHEEL
bme280pi-1.1.2.dist-info/top_level.txt
bme280pi-1.1.2.dist-info/RECORD
