Metadata-Version: 2.2
Name: bme280pi
Version: 1.1.2
Summary: bme280pi: the BME280 Sensor Reader for Raspberry Pi
Home-page: https://www.github.com/MarcoAndreaBuchmann/bme280pi
Download-URL: https://github.com/MarcoAndreaBuchmann/bme280pi/archive/v1.0.tar.gz
Author: Marco-Andrea Buchmann
Author-email: bmarcoa@gmail.com
License: MIT
Project-URL: Bug Tracker, https://github.com/MarcoAndreaBuchmann/bme280pi/issues
Project-URL: Source Code, https://github.com/MarcoAndreaBuchmann/bme280pi/
Keywords: Raspberry,Pi,Raspberry Pi,BME280,sensor,readout,temperature,pressure,humidity
Platform: Linux
Classifier: Development Status :: 5 - Production/Stable
Classifier: Intended Audience :: Developers
Classifier: Topic :: Software Development :: Build Tools
Classifier: License :: OSI Approved :: MIT License
Classifier: Programming Language :: Python :: 3
Classifier: Programming Language :: Python :: 3.4
Classifier: Programming Language :: Python :: 3.5
Classifier: Programming Language :: Python :: 3.6
Classifier: Programming Language :: Python :: 3.7
Classifier: Programming Language :: Python :: 3.8
Classifier: Programming Language :: Python :: 3.9
Classifier: Programming Language :: Python :: 3.10
Classifier: Programming Language :: Python :: 3.11
Classifier: Programming Language :: Python :: 3.12
Classifier: Programming Language :: Python :: 3.13
Requires-Python: >=3.5
License-File: LICENSE
Requires-Dist: smbus
Dynamic: author
Dynamic: author-email
Dynamic: classifier
Dynamic: description
Dynamic: description-content-type
Dynamic: download-url
Dynamic: home-page
Dynamic: keywords
Dynamic: license
Dynamic: platform
Dynamic: project-url
Dynamic: requires-dist
Dynamic: requires-python
Dynamic: summary
